{"cameraMode":{"drawMode":0,"name":"Shaded","section":"Shading Mode"},"sceneLighting":false,"audioPlay":false,"sceneViewState":{"m_AlwaysRefresh":false,"showFog":true,"showSkybox":false,"showFlares":true,"showImageEffects":true,"showParticleSystems":true,"showVisualEffectGraphs":true,"m_FxEnabled":true},"in2DMode":false,"pivot":{"x":-6.233576774597168,"y":3.705726146697998,"z":-5.162298202514648},"rotation":{"x":0.03941760212182999,"y":0.4096892178058624,"z":0.017755258828401567,"w":-0.9112282991409302},"size":5.847179889678955,"orthographic":false}